bandcampsync/__init__.py
bandcampsync/bandcamp.py
bandcampsync/config.py
bandcampsync/download.py
bandcampsync/ignores.py
bandcampsync/logger.py
bandcampsync/media.py
bandcampsync/notify.py
bandcampsync/sync.py
bandcampsync-0.7.0.data/scripts/bandcampsync
bandcampsync-0.7.0.data/scripts/bandcampsync-service
bandcampsync-0.7.0.dist-info/licenses/LICENSE
tests/__init__.py
tests/test_sync_item.py
tests/test_syncer.py
bandcampsync-0.7.0.dist-info/METADATA
bandcampsync-0.7.0.dist-info/WHEEL
bandcampsync-0.7.0.dist-info/top_level.txt
bandcampsync-0.7.0.dist-info/RECORD
