Metadata-Version: 2.4
Name: bandcampsync
Version: 0.7.0
Summary: A Python module and script to synchronise media purchased on bandcamp.com with a local directory.
Home-page: https://github.com/meeb/bandcampsync
Author: https://github.com/meeb
Author-email: meeb@meeb.org
Requires-Python: >=3.10
License-File: LICENSE
Requires-Dist: beautifulsoup4>=4.14.3
Requires-Dist: curl-cffi>=0.14.0
Requires-Dist: html5lib>=1.1
Requires-Dist: requests>=2.32.5
Dynamic: author
Dynamic: author-email
Dynamic: home-page
Dynamic: license-file
